[
    {
        "classType": "Fitness Classes 1",
        "schedule type": "Weekly Schedule",
        "people": "Michael",
        "date": "13 Nov"
    },
    {
        "classType": "Fitness Classes 2",
        "schedule type": "Weekly Schedule",
        "people": "Michael",
        "date": "13 Nov"
    },
    {
        "classType": "Fitness Classes 3",
        "schedule type": "Weekly Schedule",
        "people": "Michael",
        "date": "13 Nov"
    },
    {
       "classType": "Fitness Classes 4",
       "schedule type": "Weekly Schedule",
       "people": "Michael",
       "date": "13 Nov"
   },
   {
      "classType": "Fitness Classes 5",
      "schedule type": "Weekly Schedule",
      "people": "Michael",
      "date": "13 Nov"
  },
  {
     "classType": "Fitness Classes 6",
     "schedule type": "Weekly Schedule",
     "people": "Michael",
    "date": "13 Nov"
 },
  {
     "classType": "Fitness Classes 7",
     "schedule type": "Weekly Schedule",
     "people": "Michael",
     "date": "13 Nov"
 },
  {
     "classType": "Fitness Classes 8",
     "schedule type": "Weekly Schedule",
     "people": "Michael",
     "date": "13 Nov"
 },
  {
     "classType": "Fitness Classes 9",
     "schedule type": "Weekly Schedule",
     "people": "Michael",
     "date": "13 Nov"
 },
  {
     "classType": "Fitness Classes 10",
     "schedule type": "Weekly Schedule",
     "people": "Michael",
     "date": "13 Nov"
 },
  {
     "classType": "Fitness Classes 11",
     "schedule type": "Weekly Schedule",
     "people": "Michael",
     "date": "13 Nov"
 },
  {
     "classType": "Fitness Classes 12",
     "schedule type": "Weekly Schedule",
     "people": "Michael",
     "date": "13 Nov"
 },
  {
     "classType": "Fitness Classes 13",
     "schedule type": "Weekly Schedule",
     "people": "Michael",
     "date": "13 Nov"
 },
  {
     "classType": "Fitness Classes 14",
     "schedule type": "Weekly Schedule",
     "people": "Michael",
     "date": "13 Nov"
 },
  {
     "classType": "Fitness Classes 15",
     "schedule type": "Weekly Schedule",
     "people": "Michael",
     "date": "13 Nov"
 },
  {
     "classType": "Fitness Classes 16",
     "schedule type": "Weekly Schedule",
     "people": "Michael",
     "date": "13 Nov"
 },
  {
     "classType": "Fitness Classes 17",
     "schedule type": "Weekly Schedule",
     "people": "Michael",
     "date": "13 Nov"
 },
  {
     "classType": "Fitness Classes 18",
     "schedule type": "Weekly Schedule",
     "people": "Michael",
     "date": "13 Nov"
 },
  {
     "classType": "Fitness Classes 19",
     "schedule type": "Weekly Schedule",
     "people": "Michael",
     "date": "13 Nov"
 },
  {
     "classType": "Fitness Classes 20",
     "schedule type": "Weekly Schedule",
     "people": "Michael",
     "date": "13 Nov"
   }
]
